AUTHORS.rst
CHANGES.rst
MANIFEST.in
README.rst
setup.py
humilis_kinesis_mapper/__init__.py
humilis_kinesis_mapper/meta.yaml.j2
humilis_kinesis_mapper/outputs.yaml.j2
humilis_kinesis_mapper/plugin.py
humilis_kinesis_mapper/resources.yaml.j2
humilis_kinesis_mapper.egg-info/PKG-INFO
humilis_kinesis_mapper.egg-info/SOURCES.txt
humilis_kinesis_mapper.egg-info/dependency_links.txt
humilis_kinesis_mapper.egg-info/entry_points.txt
humilis_kinesis_mapper.egg-info/not-zip-safe
humilis_kinesis_mapper.egg-info/requires.txt
humilis_kinesis_mapper.egg-info/top_level.txt
humilis_kinesis_mapper/lambda_function/__init__.py
humilis_kinesis_mapper/lambda_function/setup.py
humilis_kinesis_mapper/lambda_function/handler/__init__.py
humilis_kinesis_mapper/lambda_function/handler/processor/__init__.py
humilis_kinesis_mapper/lambda_function/handler/processor/core.py
humilis_kinesis_mapper/lambda_function/handler/processor/exceptions.py
humilis_kinesis_mapper/lambda_function/handler/processor/main.py