Metadata-Version: 1.1
Name: humilis-kinesis-mapper
Version: 0.1.1
Summary: Humilis kinesis stream mapper plugin
Home-page: http://github.com/InnovativeTravel/humilis-kinesis-mapper
Author: Anatoly Bubenkov, FindHotel and others
Author-email: developers@innovativetravel.eu
License: MIT
Platform: UNKNOWN
Classifier: Programming Language :: Python :: 3
Classifier: Programming Language :: Python :: 2
